Encoder/8to3_Encoder/encoder_8to3_str.v
module encoder_8to3_str(input [7:0] A , output [2:0] B);
or u1(B[2],A[4],A[5],A[6],A[7]);
or u2(B[1],A[2],A[3],A[6],A[7]);
or u3(B[0],A[1],A[3],A[5],A[7]);
endmodule

Encoder/8to3_Encoder/encoder_8to3_tb.v
module encoder_8to3_tb;
reg [7:0] A;
wire [2:0] B;
encoder_8to3_str encoder(.A(A),.B(B));
initial begin
	$dumpfile("encoder_8to3.vcd");
	$dumpvars(1,encoder_8to3_tb);
end
initial begin
	A = 8'b00000001;
	#5 A = 8'b00000010;
	#5 A = 8'b00000100;
	#5 A = 8'b00001000;
	#5 A = 8'b00010000;
	#5 A = 8'b00100000;
	#5 A = 8'b01000000;
	#5 A = 8'b10000000;
	#5 $finish;
end
always @(B)
	$display("Time = %0t \t INPUT VALUES: A = %b \t OUTPUT VALUES: B = %b ",$time,A,B);
endmodule

Encoder/8to3_Encoder/encoder_8to3.vcd
$date
	Mon Feb  6 09:41:20 2023
$end
$version
	Icarus Verilog
$end
$timescale
	1s
$end
$scope module encoder_8to3_tb $end
$var wire 3 ! B [2:0] $end
$var reg 8 " A [7:0] $end
$upscope $end
$enddefinitions $end
#0
$dumpvars
b1 "
b0 !
$end
#5
b1 !
b10 "
#10
b10 !
b100 "
#15
b11 !
b1000 "
#20
b100 !
b10000 "
#25
b101 !
b100000 "
#30
b110 !
b1000000 "
#35
b111 !
b10000000 "
