mux/mux_8to1/mux_8to1_glr.v
module mux_8to1_glr(input D0,D1,D2,D3,D4,D5,D6,D7,input [2:0] S,output Y);
wire inv0,inv1,inv2;
wire a0,a1,a2,a3,a4,a5,a6,a7;
not n1(inv0,S[0]);
not n2(inv1,S[1]);
not n3(inv2,S[2]);
and u1(a0,inv0,inv1,inv2,D0);
and u2(a1,inv0,inv1,S[0],D1);
and u3(a2,inv0,S[1],inv2,D2);
and u4(a3,inv0,S[1],S[0],D3);
and u5(a4,S[2],inv1,inv2,D4);
and u6(a5,S[2],inv1,S[0],D5);
and u7(a6,S[2],S[1],inv0,D6);
and u8(a7,S[2],S[1],S[0],D7);
or res(Y,a0,a1,a2,a3,a4,a5,a6,a7);
endmodule

mux/mux_8to1/mux_8to1_tb.v
module mux_8to1_tb;
reg D0,D1,D2,D3,D4,D5,D6,D7;
reg [2:0] S;
wire Y;
mux_8to1_glr mux(.D0(D0),.D1(D1),.D2(D2),.D3(D3),.D4(D4),.D5(D5),.D6(D6),.D7(D7),.S(S),.Y(Y));
initial begin
	$dumpfile("mux_8to1.vcd");
	$dumpvars(1,mux_8to1_tb);
end
initial begin
	{D0,D1,D2,D3,D4,D5,D6,D7} = $random % 8;
	#5 S = 3'b000;
	{D0,D1,D2,D3,D4,D5,D6,D7} = $random % 8;
        #5 S = 3'b001;
	{D0,D1,D2,D3,D4,D5,D6,D7} = $random % 8;
        #5 S = 3'b010;
	{D0,D1,D2,D3,D4,D5,D6,D7} = $random % 8;
        #5 S = 3'b011;
	{D0,D1,D2,D3,D4,D5,D6,D7} = $random % 8;
        #5 S = 3'b100;
	{D0,D1,D2,D3,D4,D5,D6,D7} = $random % 8;
        #5 S = 3'b101;
	{D0,D1,D2,D3,D4,D5,D6,D7} = $random % 8;
        #5 S = 3'b110;
	{D0,D1,D2,D3,D4,D5,D6,D7} = $random % 8;
        #5 S = 3'b111;
	#5 $finish;
end
always @(Y)
	$display("Time = %0t \t INPUT VALUES: D0 D1 D2 D3 D4 D5 D6 D7 = %b%b%b%b%b%b%b%b \t S = %b \t OUTPUT VALUES: Y = %b",$time,D0,D1,D2,D3,D4,D5,D6,D7,S,Y);
endmodule

mux/mux_8to1/mux_8to1.vcd
$date
	Mon Feb  6 10:11:33 2023
$end
$version
	Icarus Verilog
$end
$timescale
	1s
$end
$scope module mux_8to1_tb $end
$var wire 1 ! Y $end
$var reg 1 " D0 $end
$var reg 1 # D1 $end
$var reg 1 $ D2 $end
$var reg 1 % D3 $end
$var reg 1 & D4 $end
$var reg 1 ' D5 $end
$var reg 1 ( D6 $end
$var reg 1 ) D7 $end
$var reg 3 * S [2:0] $end
$upscope $end
$enddefinitions $end
#0
$dumpvars
bx *
0)
0(
1'
0&
0%
0$
0#
0"
x!
$end
#5
1!
1"
1#
1$
1%
1&
0'
1)
b0 *
#10
0!
b1 *
#15
1!
1(
b10 *
#20
0!
0"
0#
0$
0%
0&
1'
0(
b11 *
#25
b100 *
#30
1!
1"
1#
1$
1%
1&
b101 *
#35
1!
0'
1(
0)
b110 *
#40
0!
b111 *
