Decoder/3to8_Decoder/decoder_3to8_beh.v
module decoder_3to8_beh(input [2:0] I, output reg [7:0] O);
always @(I) begin
	case(I)
		3'b000: {O[7],O[6],O[5],O[4],O[3],O[2],O[1],O[0]} = 8'b10000000;
		3'b001: {O[7],O[6],O[5],O[4],O[3],O[2],O[1],O[0]} = 8'b01000000;
		3'b010: {O[7],O[6],O[5],O[4],O[3],O[2],O[1],O[0]} = 8'b00100000;
		3'b011: {O[7],O[6],O[5],O[4],O[3],O[2],O[1],O[0]} = 8'b00010000;
		3'b100: {O[7],O[6],O[5],O[4],O[3],O[2],O[1],O[0]} = 8'b00001000;
		3'b101: {O[7],O[6],O[5],O[4],O[3],O[2],O[1],O[0]} = 8'b00000100;
		3'b110: {O[7],O[6],O[5],O[4],O[3],O[2],O[1],O[0]} = 8'b00000010;
		3'b111: {O[7],O[6],O[5],O[4],O[3],O[2],O[1],O[0]} = 8'b00000001;
	endcase
end
endmodule

Decoder/3to8_Decoder/decoder_3to8_tb.v
module decoder_3to8_tb;
reg [2:0]I;
wire [7:0]O;
decoder_3to8_beh decoder(.I(I),.O(O));
initial begin
	$dumpfile("decoder_3to8.vcd");
	$dumpvars(1,decoder_3to8_tb);
end
initial begin
	 I[2]=1'b0;I[1]=1'b0;I[0]=1'b0;
	#5 I[2]=1'b0;I[1]=1'b0;I[0]=1'b1;
	#5 I[2]=1'b0;I[1]=1'b1;I[0]=1'b0;
	#5 I[2]=1'b0;I[1]=1'b1;I[0]=1'b1;
	#5 I[2]=1'b1;I[1]=1'b0;I[0]=1'b0;
	#5 I[2]=1'b1;I[1]=1'b0;I[0]=1'b1;
	#5 I[2]=1'b1;I[1]=1'b1;I[0]=1'b0;
	#5 I[2]=1'b1;I[1]=1'b1;I[0]=1'b1;
	#5 $finish;
end
always @(O)
	$display("Time=%0t \t INPUT VALUES: I = %b \t OUTPUT VALUES: O = %b",$time,I,O);
endmodule

Decoder/3to8_Decoder/decoder_3to8.vcd
$date
	Mon Feb  6 01:44:32 2023
$end
$version
	Icarus Verilog
$end
$timescale
	1s
$end
$scope module decoder_3to8_tb $end
$var wire 8 ! O [7:0] $end
$var reg 3 " I [2:0] $end
$upscope $end
$enddefinitions $end
#0
$dumpvars
b0 "
b10000000 !
$end
#5
b1000000 !
b1 "
#10
b100000 !
b10 "
#15
b10000 !
b11 "
#20
b1000 !
b100 "
#25
b100 !
b101 "
#30
b10 !
b110 "
#35
b1 !
b111 "
