graytobin_convertor/graytobin.v
module graytobin(input [3:0] G , output [3:0] B);
assign B[3] = G[3];
assign B[2] = G[3] ^ G [2];
assign B[1] = G[3] ^ G[2] ^ G[1];
assign B[0] = G[3] ^ G[2] ^ G[1] ^ G[0];
endmodule

graytobin_convertor/graytobin_tb.v
module graytobin_tb;
reg [3:0] G;
wire [3:0] B;
graytobin gtb (.G(G),.B(B));
initial begin
	$dumpfile("graytobin.vcd");
	$dumpvars(1,graytobin_tb);
end
always
begin
	G <= 0;
	#5 G <= 1;
	#5 G <= 2;
	#5 G <= 3;
	#5 G <= 4;
	#5 G <= 5;
	#5 G <= 6;
	#5 G <= 7;
	#5 G <= 8;
	#5 G <= 9;
	#5 G <=10;
	#5 G <=11;
	#5 G <=12;
	#5 G <=13;
	#5 G <=14;
	#5 G <=15;
	#5 $finish;
end
always @(B[3],B[2],B[1],B[0])
	$display("Time = %0t \t INPUT VALUES: G4 G3 G2 G1 = %b%b%b%b \t OUTPUT VALUES: B4 B3 B2 B1 = %b%b%b%b",$time,G[3],G[2],G[1],G[0],B[3],B[2],B[1],B[0]);
endmodule

graytobin_convertor/graytobin.vcd
$date
	Mon Feb  6 11:45:00 2023
$end
$version
	Icarus Verilog
$end
$timescale
	1s
$end
$scope module graytobin_tb $end
$var wire 4 ! B [3:0] $end
$var reg 4 " G [3:0] $end
$upscope $end
$enddefinitions $end
#0
$dumpvars
b0 "
b0 !
$end
#5
b1 !
b1 "
#10
b11 !
b10 "
#15
b10 !
b11 "
#20
b111 !
b100 "
#25
b110 !
b101 "
#30
b100 !
b110 "
#35
b101 !
b111 "
#40
b1111 !
b1000 "
#45
b1110 !
b1001 "
#50
b1100 !
b1010 "
#55
b1101 !
b1011 "
#60
b1000 !
b1100 "
#65
b1001 !
b1101 "
#70
b1011 !
b1110 "
#75
b1010 !
b1111 "
