bintogray_convertor/bintogray.v
module bintogray(input [3:0] B , output [3:0] G);
assign G[3] = B[3];
assign G[2] = B[3] ^ B[2];
assign G[1] = B[2] ^ B[1];
assign G[0] = B[1] ^ B[0];
endmodule

bintogray_convertor/bintogray_tb.v
module bintogray_tb;
reg [3:0] B;
wire [3:0] G;
bintogray btg(.B(B),.G(G));
initial begin
	$dumpfile("bintogray.vcd");
	$dumpvars(1,bintogray_tb);
end
always
begin
	B <= 0;
	#5 B <= 1;
	#5 B <= 2;
	#5 B <= 3;
	#5 B <= 4;
	#5 B <= 5;
	#5 B <= 6;
	#5 B <= 7;
	#5 B <= 8;
	#5 B <= 9;
	#5 B <=10;
	#5 B <=11;
	#5 B <=12;
	#5 B <=13;
	#5 B <=14;
	#5 B <=15;
	#5 $finish;
end
always @(G[3],G[2],G[1],G[0])
	$display("Time = %0t \t INPUT VALUES: B4 B3 B2 B1 = %b%b%b%b \t OUTPUT VALUES: G4 G3 G2 G1 = %b%b%b%b",$time,B[3],B[2],B[1],B[0],G[3],G[2],G[1],G[0]);
endmodule

bintogray_convertor/bintogray.vcd
$date
	Mon Feb  6 11:32:06 2023
$end
$version
	Icarus Verilog
$end
$timescale
	1s
$end
$scope module bintogray_tb $end
$var wire 4 ! G [3:0] $end
$var reg 4 " B [3:0] $end
$upscope $end
$enddefinitions $end
#0
$dumpvars
b0 "
b0 !
$end
#5
b1 !
b1 "
#10
b11 !
b10 "
#15
b10 !
b11 "
#20
b110 !
b100 "
#25
b111 !
b101 "
#30
b101 !
b110 "
#35
b100 !
b111 "
#40
b1100 !
b1000 "
#45
b1101 !
b1001 "
#50
b1111 !
b1010 "
#55
b1110 !
b1011 "
#60
b1010 !
b1100 "
#65
b1011 !
b1101 "
#70
b1001 !
b1110 "
#75
b1000 !
b1111 "
