demux/demux_1to8/demux_1to8_glr.v
module demux_1to8_glr(input D,input [2:0] S,output Y0,Y1,Y2,Y3,Y4,Y5,Y6,Y7);
wire inv0,inv1,inv2;
not n1(inv0,S[0]);
not n2(inv1,S[1]);
not n3(inv2,S[2]);
and u1(Y0,inv2,inv1,inv0,D);
and u2(Y1,inv2,inv1,S[0],D);
and u3(Y2,inv2,S[1],inv0,D);
and u4(Y3,inv2,S[1],S[0],D);
and u5(Y4,S[2],inv1,inv0,D);
and u6(Y5,S[2],inv1,S[0],D);
and u7(Y6,S[2],S[1],inv0,D);
and u8(Y7,S[2],S[1],S[0],D);
endmodule

demux/demux_1to8/demux_1to8_tb.v
module demux_1to8_tb;
reg D;
reg [2:0] S;
output Y0,Y1,Y2,Y3,Y4,Y5,Y6,Y7;
demux_1to8_glr demux(.D(D),.S(S),.Y7(Y7),.Y6(Y6),.Y5(Y5),.Y4(Y4),.Y3(Y3),.Y2(Y2),.Y1(Y1),.Y0(Y0));
initial begin 
	$dumpfile("demux_1to8.vcd");
	$dumpvars(1,demux_1to8_tb);
end
initial begin
	D = $random;
	#5 S = 000;
	D = $random;
	#5 S = 001;
	D = $random;
        #5 S = 010;
	D = $random;
        #5 S = 011;
	D = $random;
        #5 S = 100;
	D = $random;
        #5 S = 101;
	D = $random;
        #5 S = 110;
	D = $random;
        #5 S = 111;
	#5 $finish;
end
always @(Y0,Y1,Y2,Y3,Y4,Y5,Y6,Y7)
	$display("Time = %0t \t INPUT VALUES: D = %b S = %b \t OUTPUT VALUES: Y7 Y6 Y5 Y4 Y3 Y2 Y1 Y0 = %b%b%b%b%b%b%b%b",$time,D,S,Y7,Y6,Y5,Y4,Y3,Y2,Y1,Y0);
endmodule

demux/demux_1to8/demux_1to8.vcd
$date
	Mon Feb  6 10:59:06 2023
$end
$version
	Icarus Verilog
$end
$timescale
	1s
$end
$scope module demux_1to8_tb $end
$var wire 1 ! Y7 $end
$var wire 1 " Y6 $end
$var wire 1 # Y5 $end
$var wire 1 $ Y4 $end
$var wire 1 % Y3 $end
$var wire 1 & Y2 $end
$var wire 1 ' Y1 $end
$var wire 1 ( Y0 $end
$var reg 1 ) D $end
$var reg 3 * S [2:0] $end
$upscope $end
$enddefinitions $end
#0
$dumpvars
bx *
0)
0(
0'
0&
0%
0$
0#
0"
0!
$end
#5
1(
1)
b0 *
#10
0(
1'
b1 *
#15
1&
0'
b10 *
#20
0&
1%
b11 *
#25
1$
0%
b100 *
#30
0$
1#
b101 *
#35
0#
0)
b110 *
#40
b111 *
